pyproject_pyupgrade/__init__.py
pyproject_pyupgrade/__main__.py
pyproject_pyupgrade/cli.py
pyproject_pyupgrade/config.py
pyproject_pyupgrade/py.typed
pyproject_pyupgrade-0.1.1.dist-info/LICENSE
pyproject_pyupgrade-0.1.1.dist-info/METADATA
pyproject_pyupgrade-0.1.1.dist-info/WHEEL
pyproject_pyupgrade-0.1.1.dist-info/entry_points.txt
pyproject_pyupgrade-0.1.1.dist-info/RECORD
