Metadata-Version: 2.1
Name: pyproject-pyupgrade
Version: 0.1.1
Summary: Pyupgrade wrapper to supply configuration via pyproject.toml
License: MIT
Author: Dmytro Selishchev
Author-email: zibertscrem@gmail.com
Requires-Python: >=3.7,<4.0
Classifier: License :: OSI Approved :: MIT License
Classifier: Programming Language :: Python :: 3
Classifier: Programming Language :: Python :: 3.7
Classifier: Programming Language :: Python :: 3.8
Classifier: Programming Language :: Python :: 3.9
Classifier: Programming Language :: Python :: 3.10
Classifier: Programming Language :: Python :: 3.11
Classifier: Programming Language :: Python :: 3.12
Requires-Dist: pyupgrade
Project-URL: repository, https://github.com/venomlab/pyproject-pyupgrade
